hbst.cpython-39-x86_64-linux-gnu.so
hbst_python-0.1.0.dist-info/METADATA
hbst_python-0.1.0.dist-info/LICENSE.txt
hbst_python-0.1.0.dist-info/WHEEL
hbst_python-0.1.0.dist-info/RECORD
hbst_python-0.1.0.dist-info/top_level.txt
